[
	{
		"name": "SringBeginning",
		"cnName": "立春",
		"items": [
			{
				"name": "huangbaiyou",
				"cnName": "黄白游",
				"value": {
					"rgb": [ 255, 247, 153 ],
					"cymk": [ 0, 0, 50, 0 ]
				}
			},
			{
				"name": "songhua",
				"cnName": "松花",
				"value": {
					"rgb": [ 255, 238, 111 ],
					"cymk": [ 0, 5, 65, 0 ]
				}
			},
			{
				"name": "xiangye",
				"cnName": "缃叶",
				"value": {
					"rgb": [ 236, 212, 82 ],
					"cymk": [ 10, 15, 75, 5 ]
				}
			},
			{
				"name": "canghuang",
				"cnName": "苍黄",
				"value": {
					"rgb": [ 182, 160, 20 ],
					"cymk": [ 35, 35, 100, 0 ]
				}
			},
			{
				"name": "tianpiao",
				"cnName": "天缥",
				"value": {
					"rgb": [ 213, 235, 225 ],
					"cymk": [ 20, 0, 15, 0 ]
				}
			},
			{
				"name": "canglang",
				"cnName": "沧浪",
				"value": {
					"rgb": [ 177, 213, 200 ],
					"cymk": [ 35, 5, 25, 0 ]
				}
			},
			{
				"name": "cangliang",
				"cnName": "苍莨",
				"value": {
					"rgb": [ 153, 188, 172 ],
					"cymk": [ 35, 15, 35, 0 ]
				}
			},
			{
				"name": "piaobi",
				"cnName": "缥碧",
				"value": {
					"rgb": [ 128, 164, 146 ],
					"cymk": [ 55, 25, 45, 0 ]
				}
			},
			{
				"name": "liuhuang",
				"cnName": "流黄",
				"value": {
					"rgb": [ 139, 112, 66 ],
					"cymk": [ 50, 55, 80, 10 ]
				}
			},
			{
				"name": "like",
				"cnName": "栗壳",
				"value": {
					"rgb": [ 119, 80, 57 ],
					"cymk": [ 35, 5, 25, 0 ]
				}
			},
			{
				"name": "longzhan",
				"cnName": "龙战",
				"value": {
					"rgb": [ 95, 67, 33 ],
					"cymk": [ 60, 70, 95, 35 ]
				}
			},
			{
				"name": "qingli",
				"cnName": "青骊",
				"value": {
					"rgb": [ 66, 37, 23 ],
					"cymk": [ 65, 80, 90, 55 ]
				}
			},
			{
				"name": "haitianxia",
				"cnName": "海天霞",
				"value": {
					"rgb": [ 243, 166, 148 ],
					"cymk": [ 0, 145, 35, 0 ]
				}
			},
			{
				"name": "jinyun",
				"cnName": "缙云",
				"value": {
					"rgb": [ 238, 121, 89 ],
					"cymk": [ 0, 65, 60, 0 ]
				}
			},
			{
				"name": "xunhuang",
				"cnName": "𫄸黄",
				"value": {
					"rgb": [ 186, 81, 64 ],
					"cymk": [ 30, 80, 75, 0 ]
				}
			},
			{
				"name": "shanhuhe",
				"cnName": "珊瑚赫",
				"value": {
					"rgb": [ 193, 44, 31 ],
					"cymk": [ 25, 95, 100, 0 ]
				}
			}
		]
	},
	{
		"name": "RainWater",
		"cnName": "雨水",
		"items": [
			{
				"name": "yingying",
				"cnName": "盈盈",
				"value": {
					"rgb": [ 249, 211, 227 ],
					"cymk": [ 0, 25, 0, 0 ]
				}
			},
			{
				"name": "",
				"cnName": "",
				"value": {
					"rgb": [  ],
					"cymk": [  ]
				}
			},
			{
				"name": "",
				"cnName": "",
				"value": {
					"rgb": [  ],
					"cymk": [  ]
				}
			},
			{
				"name": "",
				"cnName": "",
				"value": {
					"rgb": [  ],
					"cymk": [  ]
				}
			},
			{
				"name": "",
				"cnName": "",
				"value": {
					"rgb": [  ],
					"cymk": [  ]
				}
			},
			{
				"name": "",
				"cnName": "",
				"value": {
					"rgb": [  ],
					"cymk": [  ]
				}
			},
			{
				"name": "",
				"cnName": "",
				"value": {
					"rgb": [  ],
					"cymk": [  ]
				}
			},
			{
				"name": "",
				"cnName": "",
				"value": {
					"rgb": [  ],
					"cymk": [  ]
				}
			},
			{
				"name": "",
				"cnName": "",
				"value": {
					"rgb": [  ],
					"cymk": [  ]
				}
			},
			{
				"name": "",
				"cnName": "",
				"value": {
					"rgb": [  ],
					"cymk": [  ]
				}
			},
			{
				"name": "",
				"cnName": "",
				"value": {
					"rgb": [  ],
					"cymk": [  ]
				}
			},
			{
				"name": "",
				"cnName": "",
				"value": {
					"rgb": [  ],
					"cymk": [  ]
				}
			},
			{
				"name": "",
				"cnName": "",
				"value": {
					"rgb": [  ],
					"cymk": [  ]
				}
			},
			{
				"name": "",
				"cnName": "",
				"value": {
					"rgb": [  ],
					"cymk": [  ]
				}
			},
			{
				"name": "",
				"cnName": "",
				"value": {
					"rgb": [  ],
					"cymk": [  ]
				}
			},
			{
				"name": "",
				"cnName": "",
				"value": {
					"rgb": [  ],
					"cymk": [  ]
				}
			}
		]
	},
	{
		"name": "WakingInsects",
		"cnName": "惊蛰",
		"items": [
			{
				"name": "",
				"cnName": "",
				"value": {
					"rgb": [  ],
					"cymk": [  ]
				}
			},
			{
				"name": "",
				"cnName": "",
				"value": {
					"rgb": [  ],
					"cymk": [  ]
				}
			},
			{
				"name": "",
				"cnName": "",
				"value": {
					"rgb": [  ],
					"cymk": [  ]
				}
			},
			{
				"name": "",
				"cnName": "",
				"value": {
					"rgb": [  ],
					"cymk": [  ]
				}
			},
			{
				"name": "",
				"cnName": "",
				"value": {
					"rgb": [  ],
					"cymk": [  ]
				}
			},
			{
				"name": "",
				"cnName": "",
				"value": {
					"rgb": [  ],
					"cymk": [  ]
				}
			},
			{
				"name": "",
				"cnName": "",
				"value": {
					"rgb": [  ],
					"cymk": [  ]
				}
			},
			{
				"name": "",
				"cnName": "",
				"value": {
					"rgb": [  ],
					"cymk": [  ]
				}
			},
			{
				"name": "",
				"cnName": "",
				"value": {
					"rgb": [  ],
					"cymk": [  ]
				}
			},
			{
				"name": "",
				"cnName": "",
				"value": {
					"rgb": [  ],
					"cymk": [  ]
				}
			},
			{
				"name": "",
				"cnName": "",
				"value": {
					"rgb": [  ],
					"cymk": [  ]
				}
			},
			{
				"name": "",
				"cnName": "",
				"value": {
					"rgb": [  ],
					"cymk": [  ]
				}
			},
			{
				"name": "",
				"cnName": "",
				"value": {
					"rgb": [  ],
					"cymk": [  ]
				}
			},
			{
				"name": "",
				"cnName": "",
				"value": {
					"rgb": [  ],
					"cymk": [  ]
				}
			},
			{
				"name": "",
				"cnName": "",
				"value": {
					"rgb": [  ],
					"cymk": [  ]
				}
			},
			{
				"name": "",
				"cnName": "",
				"value": {
					"rgb": [  ],
					"cymk": [  ]
				}
			}
		]
	},
	{
		"name": "SpringEquinox",
		"cnName": "春分",
		"items": [
			{
				"name": "",
				"cnName": "",
				"value": {
					"rgb": [  ],
					"cymk": [  ]
				}
			},
			{
				"name": "",
				"cnName": "",
				"value": {
					"rgb": [  ],
					"cymk": [  ]
				}
			},
			{
				"name": "",
				"cnName": "",
				"value": {
					"rgb": [  ],
					"cymk": [  ]
				}
			},
			{
				"name": "",
				"cnName": "",
				"value": {
					"rgb": [  ],
					"cymk": [  ]
				}
			},
			{
				"name": "",
				"cnName": "",
				"value": {
					"rgb": [  ],
					"cymk": [  ]
				}
			},
			{
				"name": "",
				"cnName": "",
				"value": {
					"rgb": [  ],
					"cymk": [  ]
				}
			},
			{
				"name": "",
				"cnName": "",
				"value": {
					"rgb": [  ],
					"cymk": [  ]
				}
			},
			{
				"name": "",
				"cnName": "",
				"value": {
					"rgb": [  ],
					"cymk": [  ]
				}
			},
			{
				"name": "",
				"cnName": "",
				"value": {
					"rgb": [  ],
					"cymk": [  ]
				}
			},
			{
				"name": "",
				"cnName": "",
				"value": {
					"rgb": [  ],
					"cymk": [  ]
				}
			},
			{
				"name": "",
				"cnName": "",
				"value": {
					"rgb": [  ],
					"cymk": [  ]
				}
			},
			{
				"name": "",
				"cnName": "",
				"value": {
					"rgb": [  ],
					"cymk": [  ]
				}
			},
			{
				"name": "",
				"cnName": "",
				"value": {
					"rgb": [  ],
					"cymk": [  ]
				}
			},
			{
				"name": "",
				"cnName": "",
				"value": {
					"rgb": [  ],
					"cymk": [  ]
				}
			},
			{
				"name": "",
				"cnName": "",
				"value": {
					"rgb": [  ],
					"cymk": [  ]
				}
			},
			{
				"name": "",
				"cnName": "",
				"value": {
					"rgb": [  ],
					"cymk": [  ]
				}
			}
		]
	},
	{
		"name": "PureBrightness",
		"cnName": "清明",
		"items": [
			{
				"name": "",
				"cnName": "",
				"value": {
					"rgb": [  ],
					"cymk": [  ]
				}
			},
			{
				"name": "",
				"cnName": "",
				"value": {
					"rgb": [  ],
					"cymk": [  ]
				}
			},
			{
				"name": "",
				"cnName": "",
				"value": {
					"rgb": [  ],
					"cymk": [  ]
				}
			},
			{
				"name": "",
				"cnName": "",
				"value": {
					"rgb": [  ],
					"cymk": [  ]
				}
			},
			{
				"name": "",
				"cnName": "",
				"value": {
					"rgb": [  ],
					"cymk": [  ]
				}
			},
			{
				"name": "",
				"cnName": "",
				"value": {
					"rgb": [  ],
					"cymk": [  ]
				}
			},
			{
				"name": "",
				"cnName": "",
				"value": {
					"rgb": [  ],
					"cymk": [  ]
				}
			},
			{
				"name": "",
				"cnName": "",
				"value": {
					"rgb": [  ],
					"cymk": [  ]
				}
			},
			{
				"name": "",
				"cnName": "",
				"value": {
					"rgb": [  ],
					"cymk": [  ]
				}
			},
			{
				"name": "",
				"cnName": "",
				"value": {
					"rgb": [  ],
					"cymk": [  ]
				}
			},
			{
				"name": "",
				"cnName": "",
				"value": {
					"rgb": [  ],
					"cymk": [  ]
				}
			},
			{
				"name": "",
				"cnName": "",
				"value": {
					"rgb": [  ],
					"cymk": [  ]
				}
			},
			{
				"name": "",
				"cnName": "",
				"value": {
					"rgb": [  ],
					"cymk": [  ]
				}
			},
			{
				"name": "",
				"cnName": "",
				"value": {
					"rgb": [  ],
					"cymk": [  ]
				}
			},
			{
				"name": "",
				"cnName": "",
				"value": {
					"rgb": [  ],
					"cymk": [  ]
				}
			},
			{
				"name": "",
				"cnName": "",
				"value": {
					"rgb": [  ],
					"cymk": [  ]
				}
			}
		]
	},
	{
		"name": "GrainRain",
		"cnName": "谷雨",
		"items": [
			{
				"name": "",
				"cnName": "",
				"value": {
					"rgb": [  ],
					"cymk": [  ]
				}
			},
			{
				"name": "",
				"cnName": "",
				"value": {
					"rgb": [  ],
					"cymk": [  ]
				}
			},
			{
				"name": "",
				"cnName": "",
				"value": {
					"rgb": [  ],
					"cymk": [  ]
				}
			},
			{
				"name": "",
				"cnName": "",
				"value": {
					"rgb": [  ],
					"cymk": [  ]
				}
			},
			{
				"name": "",
				"cnName": "",
				"value": {
					"rgb": [  ],
					"cymk": [  ]
				}
			},
			{
				"name": "",
				"cnName": "",
				"value": {
					"rgb": [  ],
					"cymk": [  ]
				}
			},
			{
				"name": "",
				"cnName": "",
				"value": {
					"rgb": [  ],
					"cymk": [  ]
				}
			},
			{
				"name": "",
				"cnName": "",
				"value": {
					"rgb": [  ],
					"cymk": [  ]
				}
			},
			{
				"name": "",
				"cnName": "",
				"value": {
					"rgb": [  ],
					"cymk": [  ]
				}
			},
			{
				"name": "",
				"cnName": "",
				"value": {
					"rgb": [  ],
					"cymk": [  ]
				}
			},
			{
				"name": "",
				"cnName": "",
				"value": {
					"rgb": [  ],
					"cymk": [  ]
				}
			},
			{
				"name": "",
				"cnName": "",
				"value": {
					"rgb": [  ],
					"cymk": [  ]
				}
			},
			{
				"name": "",
				"cnName": "",
				"value": {
					"rgb": [  ],
					"cymk": [  ]
				}
			},
			{
				"name": "",
				"cnName": "",
				"value": {
					"rgb": [  ],
					"cymk": [  ]
				}
			},
			{
				"name": "",
				"cnName": "",
				"value": {
					"rgb": [  ],
					"cymk": [  ]
				}
			},
			{
				"name": "",
				"cnName": "",
				"value": {
					"rgb": [  ],
					"cymk": [  ]
				}
			}
		]
	},
	{
		"name": "SummerBeginning",
		"cnName": "立夏",
		"items": [
			{
				"name": "",
				"cnName": "",
				"value": {
					"rgb": [  ],
					"cymk": [  ]
				}
			},
			{
				"name": "",
				"cnName": "",
				"value": {
					"rgb": [  ],
					"cymk": [  ]
				}
			},
			{
				"name": "",
				"cnName": "",
				"value": {
					"rgb": [  ],
					"cymk": [  ]
				}
			},
			{
				"name": "",
				"cnName": "",
				"value": {
					"rgb": [  ],
					"cymk": [  ]
				}
			},
			{
				"name": "",
				"cnName": "",
				"value": {
					"rgb": [  ],
					"cymk": [  ]
				}
			},
			{
				"name": "",
				"cnName": "",
				"value": {
					"rgb": [  ],
					"cymk": [  ]
				}
			},
			{
				"name": "",
				"cnName": "",
				"value": {
					"rgb": [  ],
					"cymk": [  ]
				}
			},
			{
				"name": "",
				"cnName": "",
				"value": {
					"rgb": [  ],
					"cymk": [  ]
				}
			},
			{
				"name": "",
				"cnName": "",
				"value": {
					"rgb": [  ],
					"cymk": [  ]
				}
			},
			{
				"name": "",
				"cnName": "",
				"value": {
					"rgb": [  ],
					"cymk": [  ]
				}
			},
			{
				"name": "",
				"cnName": "",
				"value": {
					"rgb": [  ],
					"cymk": [  ]
				}
			},
			{
				"name": "",
				"cnName": "",
				"value": {
					"rgb": [  ],
					"cymk": [  ]
				}
			},
			{
				"name": "",
				"cnName": "",
				"value": {
					"rgb": [  ],
					"cymk": [  ]
				}
			},
			{
				"name": "",
				"cnName": "",
				"value": {
					"rgb": [  ],
					"cymk": [  ]
				}
			},
			{
				"name": "",
				"cnName": "",
				"value": {
					"rgb": [  ],
					"cymk": [  ]
				}
			},
			{
				"name": "",
				"cnName": "",
				"value": {
					"rgb": [  ],
					"cymk": [  ]
				}
			}
		]
	},
	{
		"name": "LesserFullness",
		"cnName": "小满",
		"items": [
			{
				"name": "",
				"cnName": "",
				"value": {
					"rgb": [  ],
					"cymk": [  ]
				}
			},
			{
				"name": "",
				"cnName": "",
				"value": {
					"rgb": [  ],
					"cymk": [  ]
				}
			},
			{
				"name": "",
				"cnName": "",
				"value": {
					"rgb": [  ],
					"cymk": [  ]
				}
			},
			{
				"name": "",
				"cnName": "",
				"value": {
					"rgb": [  ],
					"cymk": [  ]
				}
			},
			{
				"name": "",
				"cnName": "",
				"value": {
					"rgb": [  ],
					"cymk": [  ]
				}
			},
			{
				"name": "",
				"cnName": "",
				"value": {
					"rgb": [  ],
					"cymk": [  ]
				}
			},
			{
				"name": "",
				"cnName": "",
				"value": {
					"rgb": [  ],
					"cymk": [  ]
				}
			},
			{
				"name": "",
				"cnName": "",
				"value": {
					"rgb": [  ],
					"cymk": [  ]
				}
			},
			{
				"name": "",
				"cnName": "",
				"value": {
					"rgb": [  ],
					"cymk": [  ]
				}
			},
			{
				"name": "",
				"cnName": "",
				"value": {
					"rgb": [  ],
					"cymk": [  ]
				}
			},
			{
				"name": "",
				"cnName": "",
				"value": {
					"rgb": [  ],
					"cymk": [  ]
				}
			},
			{
				"name": "",
				"cnName": "",
				"value": {
					"rgb": [  ],
					"cymk": [  ]
				}
			},
			{
				"name": "",
				"cnName": "",
				"value": {
					"rgb": [  ],
					"cymk": [  ]
				}
			},
			{
				"name": "",
				"cnName": "",
				"value": {
					"rgb": [  ],
					"cymk": [  ]
				}
			},
			{
				"name": "",
				"cnName": "",
				"value": {
					"rgb": [  ],
					"cymk": [  ]
				}
			},
			{
				"name": "",
				"cnName": "",
				"value": {
					"rgb": [  ],
					"cymk": [  ]
				}
			}
		]
	},
	{
		"name": "GrainBeard",
		"cnName": "芒种",
		"items": [
			{
				"name": "",
				"cnName": "",
				"value": {
					"rgb": [  ],
					"cymk": [  ]
				}
			},
			{
				"name": "",
				"cnName": "",
				"value": {
					"rgb": [  ],
					"cymk": [  ]
				}
			},
			{
				"name": "",
				"cnName": "",
				"value": {
					"rgb": [  ],
					"cymk": [  ]
				}
			},
			{
				"name": "",
				"cnName": "",
				"value": {
					"rgb": [  ],
					"cymk": [  ]
				}
			},
			{
				"name": "",
				"cnName": "",
				"value": {
					"rgb": [  ],
					"cymk": [  ]
				}
			},
			{
				"name": "",
				"cnName": "",
				"value": {
					"rgb": [  ],
					"cymk": [  ]
				}
			},
			{
				"name": "",
				"cnName": "",
				"value": {
					"rgb": [  ],
					"cymk": [  ]
				}
			},
			{
				"name": "",
				"cnName": "",
				"value": {
					"rgb": [  ],
					"cymk": [  ]
				}
			},
			{
				"name": "",
				"cnName": "",
				"value": {
					"rgb": [  ],
					"cymk": [  ]
				}
			},
			{
				"name": "",
				"cnName": "",
				"value": {
					"rgb": [  ],
					"cymk": [  ]
				}
			},
			{
				"name": "",
				"cnName": "",
				"value": {
					"rgb": [  ],
					"cymk": [  ]
				}
			},
			{
				"name": "",
				"cnName": "",
				"value": {
					"rgb": [  ],
					"cymk": [  ]
				}
			},
			{
				"name": "",
				"cnName": "",
				"value": {
					"rgb": [  ],
					"cymk": [  ]
				}
			},
			{
				"name": "",
				"cnName": "",
				"value": {
					"rgb": [  ],
					"cymk": [  ]
				}
			},
			{
				"name": "",
				"cnName": "",
				"value": {
					"rgb": [  ],
					"cymk": [  ]
				}
			},
			{
				"name": "",
				"cnName": "",
				"value": {
					"rgb": [  ],
					"cymk": [  ]
				}
			}
		]
	},
	{
		"name": "SummerSolstice",
		"cnName": "夏至",
		"items": [
			{
				"name": "",
				"cnName": "",
				"value": {
					"rgb": [  ],
					"cymk": [  ]
				}
			},
			{
				"name": "",
				"cnName": "",
				"value": {
					"rgb": [  ],
					"cymk": [  ]
				}
			},
			{
				"name": "",
				"cnName": "",
				"value": {
					"rgb": [  ],
					"cymk": [  ]
				}
			},
			{
				"name": "",
				"cnName": "",
				"value": {
					"rgb": [  ],
					"cymk": [  ]
				}
			},
			{
				"name": "",
				"cnName": "",
				"value": {
					"rgb": [  ],
					"cymk": [  ]
				}
			},
			{
				"name": "",
				"cnName": "",
				"value": {
					"rgb": [  ],
					"cymk": [  ]
				}
			},
			{
				"name": "",
				"cnName": "",
				"value": {
					"rgb": [  ],
					"cymk": [  ]
				}
			},
			{
				"name": "",
				"cnName": "",
				"value": {
					"rgb": [  ],
					"cymk": [  ]
				}
			},
			{
				"name": "",
				"cnName": "",
				"value": {
					"rgb": [  ],
					"cymk": [  ]
				}
			},
			{
				"name": "",
				"cnName": "",
				"value": {
					"rgb": [  ],
					"cymk": [  ]
				}
			},
			{
				"name": "",
				"cnName": "",
				"value": {
					"rgb": [  ],
					"cymk": [  ]
				}
			},
			{
				"name": "",
				"cnName": "",
				"value": {
					"rgb": [  ],
					"cymk": [  ]
				}
			},
			{
				"name": "",
				"cnName": "",
				"value": {
					"rgb": [  ],
					"cymk": [  ]
				}
			},
			{
				"name": "",
				"cnName": "",
				"value": {
					"rgb": [  ],
					"cymk": [  ]
				}
			},
			{
				"name": "",
				"cnName": "",
				"value": {
					"rgb": [  ],
					"cymk": [  ]
				}
			},
			{
				"name": "",
				"cnName": "",
				"value": {
					"rgb": [  ],
					"cymk": [  ]
				}
			}
		]
	},
	{
		"name": "LesserHeat",
		"cnName": "小暑",
		"items": [
			{
				"name": "",
				"cnName": "",
				"value": {
					"rgb": [  ],
					"cymk": [  ]
				}
			},
			{
				"name": "",
				"cnName": "",
				"value": {
					"rgb": [  ],
					"cymk": [  ]
				}
			},
			{
				"name": "",
				"cnName": "",
				"value": {
					"rgb": [  ],
					"cymk": [  ]
				}
			},
			{
				"name": "",
				"cnName": "",
				"value": {
					"rgb": [  ],
					"cymk": [  ]
				}
			},
			{
				"name": "",
				"cnName": "",
				"value": {
					"rgb": [  ],
					"cymk": [  ]
				}
			},
			{
				"name": "",
				"cnName": "",
				"value": {
					"rgb": [  ],
					"cymk": [  ]
				}
			},
			{
				"name": "",
				"cnName": "",
				"value": {
					"rgb": [  ],
					"cymk": [  ]
				}
			},
			{
				"name": "",
				"cnName": "",
				"value": {
					"rgb": [  ],
					"cymk": [  ]
				}
			},
			{
				"name": "",
				"cnName": "",
				"value": {
					"rgb": [  ],
					"cymk": [  ]
				}
			},
			{
				"name": "",
				"cnName": "",
				"value": {
					"rgb": [  ],
					"cymk": [  ]
				}
			},
			{
				"name": "",
				"cnName": "",
				"value": {
					"rgb": [  ],
					"cymk": [  ]
				}
			},
			{
				"name": "",
				"cnName": "",
				"value": {
					"rgb": [  ],
					"cymk": [  ]
				}
			},
			{
				"name": "",
				"cnName": "",
				"value": {
					"rgb": [  ],
					"cymk": [  ]
				}
			},
			{
				"name": "",
				"cnName": "",
				"value": {
					"rgb": [  ],
					"cymk": [  ]
				}
			},
			{
				"name": "",
				"cnName": "",
				"value": {
					"rgb": [  ],
					"cymk": [  ]
				}
			},
			{
				"name": "",
				"cnName": "",
				"value": {
					"rgb": [  ],
					"cymk": [  ]
				}
			}
		]
	},
	{
		"name": "GreaterHeat",
		"cnName": "大暑",
		"items": [
			{
				"name": "",
				"cnName": "",
				"value": {
					"rgb": [  ],
					"cymk": [  ]
				}
			},
			{
				"name": "",
				"cnName": "",
				"value": {
					"rgb": [  ],
					"cymk": [  ]
				}
			},
			{
				"name": "",
				"cnName": "",
				"value": {
					"rgb": [  ],
					"cymk": [  ]
				}
			},
			{
				"name": "",
				"cnName": "",
				"value": {
					"rgb": [  ],
					"cymk": [  ]
				}
			},
			{
				"name": "",
				"cnName": "",
				"value": {
					"rgb": [  ],
					"cymk": [  ]
				}
			},
			{
				"name": "",
				"cnName": "",
				"value": {
					"rgb": [  ],
					"cymk": [  ]
				}
			},
			{
				"name": "",
				"cnName": "",
				"value": {
					"rgb": [  ],
					"cymk": [  ]
				}
			},
			{
				"name": "",
				"cnName": "",
				"value": {
					"rgb": [  ],
					"cymk": [  ]
				}
			},
			{
				"name": "",
				"cnName": "",
				"value": {
					"rgb": [  ],
					"cymk": [  ]
				}
			},
			{
				"name": "",
				"cnName": "",
				"value": {
					"rgb": [  ],
					"cymk": [  ]
				}
			},
			{
				"name": "",
				"cnName": "",
				"value": {
					"rgb": [  ],
					"cymk": [  ]
				}
			},
			{
				"name": "",
				"cnName": "",
				"value": {
					"rgb": [  ],
					"cymk": [  ]
				}
			},
			{
				"name": "",
				"cnName": "",
				"value": {
					"rgb": [  ],
					"cymk": [  ]
				}
			},
			{
				"name": "",
				"cnName": "",
				"value": {
					"rgb": [  ],
					"cymk": [  ]
				}
			},
			{
				"name": "",
				"cnName": "",
				"value": {
					"rgb": [  ],
					"cymk": [  ]
				}
			},
			{
				"name": "",
				"cnName": "",
				"value": {
					"rgb": [  ],
					"cymk": [  ]
				}
			}
		]
	},
	{
		"name": "AutumnBeginning",
		"cnName": "立秋",
		"items": [
			{
				"name": "",
				"cnName": "",
				"value": {
					"rgb": [  ],
					"cymk": [  ]
				}
			},
			{
				"name": "",
				"cnName": "",
				"value": {
					"rgb": [  ],
					"cymk": [  ]
				}
			},
			{
				"name": "",
				"cnName": "",
				"value": {
					"rgb": [  ],
					"cymk": [  ]
				}
			},
			{
				"name": "",
				"cnName": "",
				"value": {
					"rgb": [  ],
					"cymk": [  ]
				}
			},
			{
				"name": "",
				"cnName": "",
				"value": {
					"rgb": [  ],
					"cymk": [  ]
				}
			},
			{
				"name": "",
				"cnName": "",
				"value": {
					"rgb": [  ],
					"cymk": [  ]
				}
			},
			{
				"name": "",
				"cnName": "",
				"value": {
					"rgb": [  ],
					"cymk": [  ]
				}
			},
			{
				"name": "",
				"cnName": "",
				"value": {
					"rgb": [  ],
					"cymk": [  ]
				}
			},
			{
				"name": "",
				"cnName": "",
				"value": {
					"rgb": [  ],
					"cymk": [  ]
				}
			},
			{
				"name": "",
				"cnName": "",
				"value": {
					"rgb": [  ],
					"cymk": [  ]
				}
			},
			{
				"name": "",
				"cnName": "",
				"value": {
					"rgb": [  ],
					"cymk": [  ]
				}
			},
			{
				"name": "",
				"cnName": "",
				"value": {
					"rgb": [  ],
					"cymk": [  ]
				}
			},
			{
				"name": "",
				"cnName": "",
				"value": {
					"rgb": [  ],
					"cymk": [  ]
				}
			},
			{
				"name": "",
				"cnName": "",
				"value": {
					"rgb": [  ],
					"cymk": [  ]
				}
			},
			{
				"name": "",
				"cnName": "",
				"value": {
					"rgb": [  ],
					"cymk": [  ]
				}
			},
			{
				"name": "",
				"cnName": "",
				"value": {
					"rgb": [  ],
					"cymk": [  ]
				}
			}
		]
	},
	{
		"name": "HeatEnd",
		"cnName": "处暑",
		"items": [
			{
				"name": "",
				"cnName": "",
				"value": {
					"rgb": [  ],
					"cymk": [  ]
				}
			},
			{
				"name": "",
				"cnName": "",
				"value": {
					"rgb": [  ],
					"cymk": [  ]
				}
			},
			{
				"name": "",
				"cnName": "",
				"value": {
					"rgb": [  ],
					"cymk": [  ]
				}
			},
			{
				"name": "",
				"cnName": "",
				"value": {
					"rgb": [  ],
					"cymk": [  ]
				}
			},
			{
				"name": "",
				"cnName": "",
				"value": {
					"rgb": [  ],
					"cymk": [  ]
				}
			},
			{
				"name": "",
				"cnName": "",
				"value": {
					"rgb": [  ],
					"cymk": [  ]
				}
			},
			{
				"name": "",
				"cnName": "",
				"value": {
					"rgb": [  ],
					"cymk": [  ]
				}
			},
			{
				"name": "",
				"cnName": "",
				"value": {
					"rgb": [  ],
					"cymk": [  ]
				}
			},
			{
				"name": "",
				"cnName": "",
				"value": {
					"rgb": [  ],
					"cymk": [  ]
				}
			},
			{
				"name": "",
				"cnName": "",
				"value": {
					"rgb": [  ],
					"cymk": [  ]
				}
			},
			{
				"name": "",
				"cnName": "",
				"value": {
					"rgb": [  ],
					"cymk": [  ]
				}
			},
			{
				"name": "",
				"cnName": "",
				"value": {
					"rgb": [  ],
					"cymk": [  ]
				}
			},
			{
				"name": "",
				"cnName": "",
				"value": {
					"rgb": [  ],
					"cymk": [  ]
				}
			},
			{
				"name": "",
				"cnName": "",
				"value": {
					"rgb": [  ],
					"cymk": [  ]
				}
			},
			{
				"name": "",
				"cnName": "",
				"value": {
					"rgb": [  ],
					"cymk": [  ]
				}
			},
			{
				"name": "",
				"cnName": "",
				"value": {
					"rgb": [  ],
					"cymk": [  ]
				}
			}
		]
	},
	{
		"name": "WhiteDew",
		"cnName": "白露",
		"items": [
			{
				"name": "",
				"cnName": "",
				"value": {
					"rgb": [  ],
					"cymk": [  ]
				}
			},
			{
				"name": "",
				"cnName": "",
				"value": {
					"rgb": [  ],
					"cymk": [  ]
				}
			},
			{
				"name": "",
				"cnName": "",
				"value": {
					"rgb": [  ],
					"cymk": [  ]
				}
			},
			{
				"name": "",
				"cnName": "",
				"value": {
					"rgb": [  ],
					"cymk": [  ]
				}
			},
			{
				"name": "",
				"cnName": "",
				"value": {
					"rgb": [  ],
					"cymk": [  ]
				}
			},
			{
				"name": "",
				"cnName": "",
				"value": {
					"rgb": [  ],
					"cymk": [  ]
				}
			},
			{
				"name": "",
				"cnName": "",
				"value": {
					"rgb": [  ],
					"cymk": [  ]
				}
			},
			{
				"name": "",
				"cnName": "",
				"value": {
					"rgb": [  ],
					"cymk": [  ]
				}
			},
			{
				"name": "",
				"cnName": "",
				"value": {
					"rgb": [  ],
					"cymk": [  ]
				}
			},
			{
				"name": "",
				"cnName": "",
				"value": {
					"rgb": [  ],
					"cymk": [  ]
				}
			},
			{
				"name": "",
				"cnName": "",
				"value": {
					"rgb": [  ],
					"cymk": [  ]
				}
			},
			{
				"name": "",
				"cnName": "",
				"value": {
					"rgb": [  ],
					"cymk": [  ]
				}
			},
			{
				"name": "",
				"cnName": "",
				"value": {
					"rgb": [  ],
					"cymk": [  ]
				}
			},
			{
				"name": "",
				"cnName": "",
				"value": {
					"rgb": [  ],
					"cymk": [  ]
				}
			},
			{
				"name": "",
				"cnName": "",
				"value": {
					"rgb": [  ],
					"cymk": [  ]
				}
			},
			{
				"name": "",
				"cnName": "",
				"value": {
					"rgb": [  ],
					"cymk": [  ]
				}
			}
		]
	},
	{
		"name": "AutumnEquinox",
		"cnName": "秋分",
		"items": [
			{
				"name": "",
				"cnName": "",
				"value": {
					"rgb": [  ],
					"cymk": [  ]
				}
			},
			{
				"name": "",
				"cnName": "",
				"value": {
					"rgb": [  ],
					"cymk": [  ]
				}
			},
			{
				"name": "",
				"cnName": "",
				"value": {
					"rgb": [  ],
					"cymk": [  ]
				}
			},
			{
				"name": "",
				"cnName": "",
				"value": {
					"rgb": [  ],
					"cymk": [  ]
				}
			},
			{
				"name": "",
				"cnName": "",
				"value": {
					"rgb": [  ],
					"cymk": [  ]
				}
			},
			{
				"name": "",
				"cnName": "",
				"value": {
					"rgb": [  ],
					"cymk": [  ]
				}
			},
			{
				"name": "",
				"cnName": "",
				"value": {
					"rgb": [  ],
					"cymk": [  ]
				}
			},
			{
				"name": "",
				"cnName": "",
				"value": {
					"rgb": [  ],
					"cymk": [  ]
				}
			},
			{
				"name": "",
				"cnName": "",
				"value": {
					"rgb": [  ],
					"cymk": [  ]
				}
			},
			{
				"name": "",
				"cnName": "",
				"value": {
					"rgb": [  ],
					"cymk": [  ]
				}
			},
			{
				"name": "",
				"cnName": "",
				"value": {
					"rgb": [  ],
					"cymk": [  ]
				}
			},
			{
				"name": "",
				"cnName": "",
				"value": {
					"rgb": [  ],
					"cymk": [  ]
				}
			},
			{
				"name": "",
				"cnName": "",
				"value": {
					"rgb": [  ],
					"cymk": [  ]
				}
			},
			{
				"name": "",
				"cnName": "",
				"value": {
					"rgb": [  ],
					"cymk": [  ]
				}
			},
			{
				"name": "",
				"cnName": "",
				"value": {
					"rgb": [  ],
					"cymk": [  ]
				}
			},
			{
				"name": "",
				"cnName": "",
				"value": {
					"rgb": [  ],
					"cymk": [  ]
				}
			}
		]
	},
	{
		"name": "ColdDew",
		"cnName": "寒露",
		"items": [
			{
				"name": "",
				"cnName": "",
				"value": {
					"rgb": [  ],
					"cymk": [  ]
				}
			},
			{
				"name": "",
				"cnName": "",
				"value": {
					"rgb": [  ],
					"cymk": [  ]
				}
			},
			{
				"name": "",
				"cnName": "",
				"value": {
					"rgb": [  ],
					"cymk": [  ]
				}
			},
			{
				"name": "",
				"cnName": "",
				"value": {
					"rgb": [  ],
					"cymk": [  ]
				}
			},
			{
				"name": "",
				"cnName": "",
				"value": {
					"rgb": [  ],
					"cymk": [  ]
				}
			},
			{
				"name": "",
				"cnName": "",
				"value": {
					"rgb": [  ],
					"cymk": [  ]
				}
			},
			{
				"name": "",
				"cnName": "",
				"value": {
					"rgb": [  ],
					"cymk": [  ]
				}
			},
			{
				"name": "",
				"cnName": "",
				"value": {
					"rgb": [  ],
					"cymk": [  ]
				}
			},
			{
				"name": "",
				"cnName": "",
				"value": {
					"rgb": [  ],
					"cymk": [  ]
				}
			},
			{
				"name": "",
				"cnName": "",
				"value": {
					"rgb": [  ],
					"cymk": [  ]
				}
			},
			{
				"name": "",
				"cnName": "",
				"value": {
					"rgb": [  ],
					"cymk": [  ]
				}
			},
			{
				"name": "",
				"cnName": "",
				"value": {
					"rgb": [  ],
					"cymk": [  ]
				}
			},
			{
				"name": "",
				"cnName": "",
				"value": {
					"rgb": [  ],
					"cymk": [  ]
				}
			},
			{
				"name": "",
				"cnName": "",
				"value": {
					"rgb": [  ],
					"cymk": [  ]
				}
			},
			{
				"name": "",
				"cnName": "",
				"value": {
					"rgb": [  ],
					"cymk": [  ]
				}
			},
			{
				"name": "",
				"cnName": "",
				"value": {
					"rgb": [  ],
					"cymk": [  ]
				}
			}
		]
	},
	{
		"name": "FrostDescent",
		"cnName": "霜降",
		"items": [
			{
				"name": "",
				"cnName": "",
				"value": {
					"rgb": [  ],
					"cymk": [  ]
				}
			},
			{
				"name": "",
				"cnName": "",
				"value": {
					"rgb": [  ],
					"cymk": [  ]
				}
			},
			{
				"name": "",
				"cnName": "",
				"value": {
					"rgb": [  ],
					"cymk": [  ]
				}
			},
			{
				"name": "",
				"cnName": "",
				"value": {
					"rgb": [  ],
					"cymk": [  ]
				}
			},
			{
				"name": "",
				"cnName": "",
				"value": {
					"rgb": [  ],
					"cymk": [  ]
				}
			},
			{
				"name": "",
				"cnName": "",
				"value": {
					"rgb": [  ],
					"cymk": [  ]
				}
			},
			{
				"name": "",
				"cnName": "",
				"value": {
					"rgb": [  ],
					"cymk": [  ]
				}
			},
			{
				"name": "",
				"cnName": "",
				"value": {
					"rgb": [  ],
					"cymk": [  ]
				}
			},
			{
				"name": "",
				"cnName": "",
				"value": {
					"rgb": [  ],
					"cymk": [  ]
				}
			},
			{
				"name": "",
				"cnName": "",
				"value": {
					"rgb": [  ],
					"cymk": [  ]
				}
			},
			{
				"name": "",
				"cnName": "",
				"value": {
					"rgb": [  ],
					"cymk": [  ]
				}
			},
			{
				"name": "",
				"cnName": "",
				"value": {
					"rgb": [  ],
					"cymk": [  ]
				}
			},
			{
				"name": "",
				"cnName": "",
				"value": {
					"rgb": [  ],
					"cymk": [  ]
				}
			},
			{
				"name": "",
				"cnName": "",
				"value": {
					"rgb": [  ],
					"cymk": [  ]
				}
			},
			{
				"name": "",
				"cnName": "",
				"value": {
					"rgb": [  ],
					"cymk": [  ]
				}
			},
			{
				"name": "",
				"cnName": "",
				"value": {
					"rgb": [  ],
					"cymk": [  ]
				}
			}
		]
	},
	{
		"name": "WinterBeginning",
		"cnName": "立冬",
		"items": [
			{
				"name": "",
				"cnName": "",
				"value": {
					"rgb": [  ],
					"cymk": [  ]
				}
			},
			{
				"name": "",
				"cnName": "",
				"value": {
					"rgb": [  ],
					"cymk": [  ]
				}
			},
			{
				"name": "",
				"cnName": "",
				"value": {
					"rgb": [  ],
					"cymk": [  ]
				}
			},
			{
				"name": "",
				"cnName": "",
				"value": {
					"rgb": [  ],
					"cymk": [  ]
				}
			},
			{
				"name": "",
				"cnName": "",
				"value": {
					"rgb": [  ],
					"cymk": [  ]
				}
			},
			{
				"name": "",
				"cnName": "",
				"value": {
					"rgb": [  ],
					"cymk": [  ]
				}
			},
			{
				"name": "",
				"cnName": "",
				"value": {
					"rgb": [  ],
					"cymk": [  ]
				}
			},
			{
				"name": "",
				"cnName": "",
				"value": {
					"rgb": [  ],
					"cymk": [  ]
				}
			},
			{
				"name": "",
				"cnName": "",
				"value": {
					"rgb": [  ],
					"cymk": [  ]
				}
			},
			{
				"name": "",
				"cnName": "",
				"value": {
					"rgb": [  ],
					"cymk": [  ]
				}
			},
			{
				"name": "",
				"cnName": "",
				"value": {
					"rgb": [  ],
					"cymk": [  ]
				}
			},
			{
				"name": "",
				"cnName": "",
				"value": {
					"rgb": [  ],
					"cymk": [  ]
				}
			},
			{
				"name": "",
				"cnName": "",
				"value": {
					"rgb": [  ],
					"cymk": [  ]
				}
			},
			{
				"name": "",
				"cnName": "",
				"value": {
					"rgb": [  ],
					"cymk": [  ]
				}
			},
			{
				"name": "",
				"cnName": "",
				"value": {
					"rgb": [  ],
					"cymk": [  ]
				}
			},
			{
				"name": "",
				"cnName": "",
				"value": {
					"rgb": [  ],
					"cymk": [  ]
				}
			}
		]
	},
	{
		"name": "LesserSnow",
		"cnName": "小雪",
		"items": [
			{
				"name": "",
				"cnName": "",
				"value": {
					"rgb": [  ],
					"cymk": [  ]
				}
			},
			{
				"name": "",
				"cnName": "",
				"value": {
					"rgb": [  ],
					"cymk": [  ]
				}
			},
			{
				"name": "",
				"cnName": "",
				"value": {
					"rgb": [  ],
					"cymk": [  ]
				}
			},
			{
				"name": "",
				"cnName": "",
				"value": {
					"rgb": [  ],
					"cymk": [  ]
				}
			},
			{
				"name": "",
				"cnName": "",
				"value": {
					"rgb": [  ],
					"cymk": [  ]
				}
			},
			{
				"name": "",
				"cnName": "",
				"value": {
					"rgb": [  ],
					"cymk": [  ]
				}
			},
			{
				"name": "",
				"cnName": "",
				"value": {
					"rgb": [  ],
					"cymk": [  ]
				}
			},
			{
				"name": "",
				"cnName": "",
				"value": {
					"rgb": [  ],
					"cymk": [  ]
				}
			},
			{
				"name": "",
				"cnName": "",
				"value": {
					"rgb": [  ],
					"cymk": [  ]
				}
			},
			{
				"name": "",
				"cnName": "",
				"value": {
					"rgb": [  ],
					"cymk": [  ]
				}
			},
			{
				"name": "",
				"cnName": "",
				"value": {
					"rgb": [  ],
					"cymk": [  ]
				}
			},
			{
				"name": "",
				"cnName": "",
				"value": {
					"rgb": [  ],
					"cymk": [  ]
				}
			},
			{
				"name": "",
				"cnName": "",
				"value": {
					"rgb": [  ],
					"cymk": [  ]
				}
			},
			{
				"name": "",
				"cnName": "",
				"value": {
					"rgb": [  ],
					"cymk": [  ]
				}
			},
			{
				"name": "",
				"cnName": "",
				"value": {
					"rgb": [  ],
					"cymk": [  ]
				}
			},
			{
				"name": "",
				"cnName": "",
				"value": {
					"rgb": [  ],
					"cymk": [  ]
				}
			}
		]
	},
	{
		"name": "GreaterSnow",
		"cnName": "大雪",
		"items": [
			{
				"name": "",
				"cnName": "",
				"value": {
					"rgb": [  ],
					"cymk": [  ]
				}
			},
			{
				"name": "",
				"cnName": "",
				"value": {
					"rgb": [  ],
					"cymk": [  ]
				}
			},
			{
				"name": "",
				"cnName": "",
				"value": {
					"rgb": [  ],
					"cymk": [  ]
				}
			},
			{
				"name": "",
				"cnName": "",
				"value": {
					"rgb": [  ],
					"cymk": [  ]
				}
			},
			{
				"name": "",
				"cnName": "",
				"value": {
					"rgb": [  ],
					"cymk": [  ]
				}
			},
			{
				"name": "",
				"cnName": "",
				"value": {
					"rgb": [  ],
					"cymk": [  ]
				}
			},
			{
				"name": "",
				"cnName": "",
				"value": {
					"rgb": [  ],
					"cymk": [  ]
				}
			},
			{
				"name": "",
				"cnName": "",
				"value": {
					"rgb": [  ],
					"cymk": [  ]
				}
			},
			{
				"name": "",
				"cnName": "",
				"value": {
					"rgb": [  ],
					"cymk": [  ]
				}
			},
			{
				"name": "",
				"cnName": "",
				"value": {
					"rgb": [  ],
					"cymk": [  ]
				}
			},
			{
				"name": "",
				"cnName": "",
				"value": {
					"rgb": [  ],
					"cymk": [  ]
				}
			},
			{
				"name": "",
				"cnName": "",
				"value": {
					"rgb": [  ],
					"cymk": [  ]
				}
			},
			{
				"name": "",
				"cnName": "",
				"value": {
					"rgb": [  ],
					"cymk": [  ]
				}
			},
			{
				"name": "",
				"cnName": "",
				"value": {
					"rgb": [  ],
					"cymk": [  ]
				}
			},
			{
				"name": "",
				"cnName": "",
				"value": {
					"rgb": [  ],
					"cymk": [  ]
				}
			},
			{
				"name": "",
				"cnName": "",
				"value": {
					"rgb": [  ],
					"cymk": [  ]
				}
			}
		]
	},
	{
		"name": "WinterSolstice",
		"cnName": "冬至",
		"items": [
			{
				"name": "",
				"cnName": "",
				"value": {
					"rgb": [  ],
					"cymk": [  ]
				}
			},
			{
				"name": "",
				"cnName": "",
				"value": {
					"rgb": [  ],
					"cymk": [  ]
				}
			},
			{
				"name": "",
				"cnName": "",
				"value": {
					"rgb": [  ],
					"cymk": [  ]
				}
			},
			{
				"name": "",
				"cnName": "",
				"value": {
					"rgb": [  ],
					"cymk": [  ]
				}
			},
			{
				"name": "",
				"cnName": "",
				"value": {
					"rgb": [  ],
					"cymk": [  ]
				}
			},
			{
				"name": "",
				"cnName": "",
				"value": {
					"rgb": [  ],
					"cymk": [  ]
				}
			},
			{
				"name": "",
				"cnName": "",
				"value": {
					"rgb": [  ],
					"cymk": [  ]
				}
			},
			{
				"name": "",
				"cnName": "",
				"value": {
					"rgb": [  ],
					"cymk": [  ]
				}
			},
			{
				"name": "",
				"cnName": "",
				"value": {
					"rgb": [  ],
					"cymk": [  ]
				}
			},
			{
				"name": "",
				"cnName": "",
				"value": {
					"rgb": [  ],
					"cymk": [  ]
				}
			},
			{
				"name": "",
				"cnName": "",
				"value": {
					"rgb": [  ],
					"cymk": [  ]
				}
			},
			{
				"name": "",
				"cnName": "",
				"value": {
					"rgb": [  ],
					"cymk": [  ]
				}
			},
			{
				"name": "",
				"cnName": "",
				"value": {
					"rgb": [  ],
					"cymk": [  ]
				}
			},
			{
				"name": "",
				"cnName": "",
				"value": {
					"rgb": [  ],
					"cymk": [  ]
				}
			},
			{
				"name": "",
				"cnName": "",
				"value": {
					"rgb": [  ],
					"cymk": [  ]
				}
			},
			{
				"name": "",
				"cnName": "",
				"value": {
					"rgb": [  ],
					"cymk": [  ]
				}
			}
		]
	},
	{
		"name": "LesserCold",
		"cnName": "小寒",
		"items": [
			{
				"name": "",
				"cnName": "",
				"value": {
					"rgb": [  ],
					"cymk": [  ]
				}
			},
			{
				"name": "",
				"cnName": "",
				"value": {
					"rgb": [  ],
					"cymk": [  ]
				}
			},
			{
				"name": "",
				"cnName": "",
				"value": {
					"rgb": [  ],
					"cymk": [  ]
				}
			},
			{
				"name": "",
				"cnName": "",
				"value": {
					"rgb": [  ],
					"cymk": [  ]
				}
			},
			{
				"name": "",
				"cnName": "",
				"value": {
					"rgb": [  ],
					"cymk": [  ]
				}
			},
			{
				"name": "",
				"cnName": "",
				"value": {
					"rgb": [  ],
					"cymk": [  ]
				}
			},
			{
				"name": "",
				"cnName": "",
				"value": {
					"rgb": [  ],
					"cymk": [  ]
				}
			},
			{
				"name": "",
				"cnName": "",
				"value": {
					"rgb": [  ],
					"cymk": [  ]
				}
			},
			{
				"name": "",
				"cnName": "",
				"value": {
					"rgb": [  ],
					"cymk": [  ]
				}
			},
			{
				"name": "",
				"cnName": "",
				"value": {
					"rgb": [  ],
					"cymk": [  ]
				}
			},
			{
				"name": "",
				"cnName": "",
				"value": {
					"rgb": [  ],
					"cymk": [  ]
				}
			},
			{
				"name": "",
				"cnName": "",
				"value": {
					"rgb": [  ],
					"cymk": [  ]
				}
			},
			{
				"name": "",
				"cnName": "",
				"value": {
					"rgb": [  ],
					"cymk": [  ]
				}
			},
			{
				"name": "",
				"cnName": "",
				"value": {
					"rgb": [  ],
					"cymk": [  ]
				}
			},
			{
				"name": "",
				"cnName": "",
				"value": {
					"rgb": [  ],
					"cymk": [  ]
				}
			},
			{
				"name": "",
				"cnName": "",
				"value": {
					"rgb": [  ],
					"cymk": [  ]
				}
			}
		]
	},
	{
		"name": "GreaterCold",
		"cnName": "大寒",
		"items": [
			{
				"name": "",
				"cnName": "",
				"value": {
					"rgb": [  ],
					"cymk": [  ]
				}
			},
			{
				"name": "",
				"cnName": "",
				"value": {
					"rgb": [  ],
					"cymk": [  ]
				}
			},
			{
				"name": "",
				"cnName": "",
				"value": {
					"rgb": [  ],
					"cymk": [  ]
				}
			},
			{
				"name": "",
				"cnName": "",
				"value": {
					"rgb": [  ],
					"cymk": [  ]
				}
			},
			{
				"name": "",
				"cnName": "",
				"value": {
					"rgb": [  ],
					"cymk": [  ]
				}
			},
			{
				"name": "",
				"cnName": "",
				"value": {
					"rgb": [  ],
					"cymk": [  ]
				}
			},
			{
				"name": "",
				"cnName": "",
				"value": {
					"rgb": [  ],
					"cymk": [  ]
				}
			},
			{
				"name": "",
				"cnName": "",
				"value": {
					"rgb": [  ],
					"cymk": [  ]
				}
			},
			{
				"name": "",
				"cnName": "",
				"value": {
					"rgb": [  ],
					"cymk": [  ]
				}
			},
			{
				"name": "",
				"cnName": "",
				"value": {
					"rgb": [  ],
					"cymk": [  ]
				}
			},
			{
				"name": "",
				"cnName": "",
				"value": {
					"rgb": [  ],
					"cymk": [  ]
				}
			},
			{
				"name": "",
				"cnName": "",
				"value": {
					"rgb": [  ],
					"cymk": [  ]
				}
			},
			{
				"name": "",
				"cnName": "",
				"value": {
					"rgb": [  ],
					"cymk": [  ]
				}
			},
			{
				"name": "",
				"cnName": "",
				"value": {
					"rgb": [  ],
					"cymk": [  ]
				}
			},
			{
				"name": "",
				"cnName": "",
				"value": {
					"rgb": [  ],
					"cymk": [  ]
				}
			},
			{
				"name": "",
				"cnName": "",
				"value": {
					"rgb": [  ],
					"cymk": [  ]
				}
			}
		]
	}
]